Metadata-Version: 2.1
Name: nonebot-plugin-aibot
Version: 0.1.2
Summary: nonebot-plugin-aibot
Requires-Python: <4.0,>=3.8
License-File: LICENSE
